aws_recommendation_a8/__init__.py
aws_recommendation_a8/cloudwatch.py
aws_recommendation_a8/cost_estimations.py
aws_recommendation_a8/dynamodb.py
aws_recommendation_a8/ebs.py
aws_recommendation_a8/ec2.py
aws_recommendation_a8/elb.py
aws_recommendation_a8/kms.py
aws_recommendation_a8/rds.py
aws_recommendation_a8/recommendation.py
aws_recommendation_a8/redshift.py
aws_recommendation_a8/s3.py
aws_recommendation_a8/truted_advisor.py
aws_recommendation_a8/utils.py
aws_recommendation_a8-0.0.20.dist-info/LICENCE
aws_recommendation_a8-0.0.20.dist-info/METADATA
aws_recommendation_a8-0.0.20.dist-info/WHEEL
aws_recommendation_a8-0.0.20.dist-info/top_level.txt
aws_recommendation_a8-0.0.20.dist-info/RECORD
